[{"model": "mylib.genre", "pk": 1, "fields": {"name": "Novel"}}, {"model": "mylib.genre", "pk": 2, "fields": {"name": "science fiction"}}, {"model": "mylib.genre", "pk": 3, "fields": {"name": "triller"}}, {"model": "mylib.genre", "pk": 4, "fields": {"name": "tragedy"}}, {"model": "mylib.genre", "pk": 5, "fields": {"name": "melodrama"}}, {"model": "mylib.genre", "pk": 6, "fields": {"name": "western"}}, {"model": "mylib.genre", "pk": 7, "fields": {"name": "fantasy"}}, {"model": "mylib.genre", "pk": 8, "fields": {"name": "tragic comedy"}}, {"model": "mylib.genre", "pk": 9, "fields": {"name": "mythology"}}, {"model": "mylib.genre", "pk": 10, "fields": {"name": "drama"}}, {"model": "mylib.genre", "pk": 11, "fields": {"name": "romance"}}, {"model": "mylib.genre", "pk": 12, "fields": {"name": "classic"}}, {"model": "mylib.genre", "pk": 13, "fields": {"name": "detective"}}, {"model": "mylib.genre", "pk": 14, "fields": {"name": "humor"}}, {"model": "mylib.genre", "pk": 15, "fields": {"name": "legend"}}]